[
  {
    "id": 1,
    "image": "/images/bg/h2-food-item-1.png",
    "title": "Prawn with Noodles",
    "price": "10"
  },
  {
    "id": 2,
    "image": "/images/bg/h2-food-item-2.png",
    "title": "Chicken Leg Fry",
    "price": "10"
  },
  {
    "id": 3,
    "image": "/images/bg/h2-food-item-3.png",
    "title": "Golden Coffee",
    "price": "10"
  },
  {
    "id": 4,
    "image": "/images/bg/h2-food-item-4.png",
    "title": "Full Chicken",
    "price": "10"
  },
  {
    "id": 5,
    "image": "/images/bg/h2-food-item-5.png",
    "title": "Mutton Kabab",
    "price": "10"
  },
  {
    "id": 6,
    "image": "/images/bg/h2-food-item-6.png",
    "title": "Prawn with Noodles",
    "price": "10"
  },
  {
    "id": 7,
    "image": "/images/bg/h2-food-item-7.png",
    "title": "Shrimps with Role",
    "price": "10"
  },
  {
    "id": 8,
    "image": "/images/bg/h2-food-item-8.png",
    "title": "Mutton with Shrimps",
    "price": "10"
  },
  {
    "id": 9,
    "image": "/images/bg/h2-food-item-1.png",
    "title": "Prawn with Noodles",
    "price": "10"
  },
  {
    "id": 10,
    "image": "/images/bg/h2-food-item-2.png",
    "title": "Chicken Leg Fry",
    "price": "10"
  },
  {
    "id": 11,
    "image": "/images/bg/h2-food-item-3.png",
    "title": "Golden Coffee",
    "price": "10"
  },

  {
    "id": 16,
    "image": "/images/bg/h2-food-item-8.png",
    "title": "Mutton with Shrimps",
    "price": "10"
  },
  {
    "id": 17,
    "image": "/images/bg/h2-food-item-1.png",
    "title": "Prawn with Noodles",
    "price": "10"
  },
  {
    "id": 18,
    "image": "/images/bg/h2-food-item-2.png",
    "title": "Chicken Leg Fry",
    "price": "10"
  },
  {
    "id": 19,
    "image": "/images/bg/h2-food-item-3.png",
    "title": "Golden Coffee",
    "price": "10"
  },
  {
    "id": 20,
    "image": "/images/bg/h2-food-item-4.png",
    "title": "Full Chicken",
    "price": "10"
  },
  {
    "id": 12,
    "image": "/images/bg/h2-food-item-4.png",
    "title": "Full Chicken",
    "price": "10"
  },
  {
    "id": 13,
    "image": "/images/bg/h2-food-item-5.png",
    "title": "Mutton Kabab",
    "price": "10"
  },
  {
    "id": 14,
    "image": "/images/bg/h2-food-item-6.png",
    "title": "Prawn with Noodles",
    "price": "10"
  },
  {
    "id": 15,
    "image": "/images/bg/h2-food-item-7.png",
    "title": "Shrimps with Role",
    "price": "10"
  },
  {
    "id": 21,
    "image": "/images/bg/h2-food-item-5.png",
    "title": "Mutton Kabab",
    "price": "10"
  },
  {
    "id": 22,
    "image": "/images/bg/h2-food-item-6.png",
    "title": "Prawn with Noodles",
    "price": "10"
  },
  {
    "id": 23,
    "image": "/images/bg/h2-food-item-7.png",
    "title": "Shrimps with Role",
    "price": "10"
  },
  {
    "id": 24,
    "image": "/images/bg/h2-food-item-8.png",
    "title": "Mutton with Shrimps",
    "price": "10"
  },
  {
    "id": 25,
    "image": "/images/bg/h2-food-item-1.png",
    "title": "Prawn with Noodles",
    "price": "10"
  },
  {
    "id": 26,
    "image": "/images/bg/h2-food-item-2.png",
    "title": "Chicken Leg Fry",
    "price": "10"
  },
  {
    "id": 27,
    "image": "/images/bg/h2-food-item-3.png",
    "title": "Golden Coffee",
    "price": "10"
  },
  {
    "id": 28,
    "image": "/images/bg/h2-food-item-4.png",
    "title": "Full Chicken",
    "price": "10"
  },
  {
    "id": 22,
    "image": "/images/bg/h2-food-item-6.png",
    "title": "Prawn with Noodles",
    "price": "10"
  },
  {
    "id": 23,
    "image": "/images/bg/h2-food-item-7.png",
    "title": "Shrimps with Role",
    "price": "10"
  },
  {
    "id": 24,
    "image": "/images/bg/h2-food-item-8.png",
    "title": "Mutton with Shrimps",
    "price": "10"
  },
  {
    "id": 25,
    "image": "/images/bg/h2-food-item-1.png",
    "title": "Prawn with Noodles",
    "price": "10"
  },
  {
    "id": 26,
    "image": "/images/bg/h2-food-item-2.png",
    "title": "Chicken Leg Fry",
    "price": "10"
  },
  {
    "id": 32,
    "image": "/images/bg/h2-food-item-6.png",
    "title": "Prawn with Noodles",
    "price": "10"
  },
  {
    "id": 33,
    "image": "/images/bg/h2-food-item-7.png",
    "title": "Shrimps with Role",
    "price": "10"
  },
  {
    "id": 34,
    "image": "/images/bg/h2-food-item-8.png",
    "title": "Mutton with Shrimps",
    "price": "10"
  },
  {
    "id": 35,
    "image": "/images/bg/h2-food-item-1.png",
    "title": "Prawn with Noodles",
    "price": "10"
  },
  {
    "id": 36,
    "image": "/images/bg/h2-food-item-2.png",
    "title": "Chicken Leg Fry",
    "price": "10"
  },
  {
    "id": 37,
    "image": "/images/bg/h2-food-item-3.png",
    "title": "Golden Coffee",
    "price": "10"
  },
  {
    "id": 88,
    "image": "/images/bg/h2-food-item-4.png",
    "title": "Full Chicken",
    "price": "10"
  },
  {
    "id": 39,
    "image": "/images/bg/h2-food-item-5.png",
    "title": "Mutton Kabab",
    "price": "10"
  },
  {
    "id": 23,
    "image": "/images/bg/h2-food-item-7.png",
    "title": "Shrimps with Role",
    "price": "10"
  },
  {
    "id": 24,
    "image": "/images/bg/h2-food-item-8.png",
    "title": "Mutton with Shrimps",
    "price": "10"
  },
  {
    "id": 25,
    "image": "/images/bg/h2-food-item-1.png",
    "title": "Prawn with Noodles",
    "price": "10"
  },
  {
    "id": 26,
    "image": "/images/bg/h2-food-item-2.png",
    "title": "Chicken Leg Fry",
    "price": "10"
  },
  {
    "id": 27,
    "image": "/images/bg/h2-food-item-3.png",
    "title": "Golden Coffee",
    "price": "10"
  },
  {
    "id": 28,
    "image": "/images/bg/h2-food-item-4.png",
    "title": "Full Chicken",
    "price": "10"
  },
  {
    "id": 22,
    "image": "/images/bg/h2-food-item-6.png",
    "title": "Prawn with Noodles",
    "price": "10"
  },
  {
    "id": 23,
    "image": "/images/bg/h2-food-item-7.png",
    "title": "Shrimps with Role",
    "price": "10"
  },
  {
    "id": 24,
    "image": "/images/bg/h2-food-item-8.png",
    "title": "Mutton with Shrimps",
    "price": "10"
  },
  {
    "id": 25,
    "image": "/images/bg/h2-food-item-1.png",
    "title": "Prawn with Noodles",
    "price": "10"
  },
  {
    "id": 26,
    "image": "/images/bg/h2-food-item-2.png",
    "title": "Chicken Leg Fry",
    "price": "10"
  },
  {
    "id": 32,
    "image": "/images/bg/h2-food-item-6.png",
    "title": "Prawn with Noodles",
    "price": "10"
  },
  {
    "id": 33,
    "image": "/images/bg/h2-food-item-7.png",
    "title": "Shrimps with Role",
    "price": "10"
  },
  {
    "id": 34,
    "image": "/images/bg/h2-food-item-8.png",
    "title": "Mutton with Shrimps",
    "price": "10"
  },
  {
    "id": 35,
    "image": "/images/bg/h2-food-item-1.png",
    "title": "Prawn with Noodles",
    "price": "10"
  },
  {
    "id": 36,
    "image": "/images/bg/h2-food-item-2.png",
    "title": "Chicken Leg Fry",
    "price": "10"
  },
  {
    "id": 37,
    "image": "/images/bg/h2-food-item-3.png",
    "title": "Golden Coffee",
    "price": "10"
  },
  {
    "id": 88,
    "image": "/images/bg/h2-food-item-4.png",
    "title": "Full Chicken",
    "price": "10"
  },
  {
    "id": 39,
    "image": "/images/bg/h2-food-item-5.png",
    "title": "Mutton Kabab",
    "price": "10"
  }
]
